bayeux/__init__.py
bayeux/_src/__init__.py
bayeux/_src/bayeux.py
bayeux/_src/debug.py
bayeux/_src/initialization.py
bayeux/_src/shared.py
bayeux/_src/types.py
bayeux/_src/mcmc/__init__.py
bayeux/_src/mcmc/blackjax.py
bayeux/_src/mcmc/flowmc.py
bayeux/_src/mcmc/numpyro.py
bayeux/_src/mcmc/nutpie.py
bayeux/_src/mcmc/tfp.py
bayeux/_src/optimize/__init__.py
bayeux/_src/optimize/jaxopt.py
bayeux/_src/optimize/optax.py
bayeux/_src/optimize/optimistix.py
bayeux/_src/optimize/shared.py
bayeux/_src/vi/__init__.py
bayeux/_src/vi/tfp.py
bayeux/mcmc/__init__.py
bayeux/optimize/__init__.py
bayeux/vi/__init__.py
bayeux_ml-0.1.15.dist-info/LICENSE
bayeux_ml-0.1.15.dist-info/WHEEL
bayeux_ml-0.1.15.dist-info/METADATA
bayeux_ml-0.1.15.dist-info/RECORD
