Metadata-Version: 2.3
Name: bayeux-ml
Version: 0.1.15
Summary: Stitching together probabilistic models and inference.
Keywords: 
Author-email: bayeux authors <bayeux@google.com>
Requires-Python: >=3.10
Classifier: License :: OSI Approved :: Apache Software License
Classifier: Intended Audience :: Science/Research
Requires-Dist: jax>=0.4.36
Requires-Dist: tensorflow-probability[jax]>=0.19.0
Requires-Dist: oryx>=0.2.9
Requires-Dist: arviz
Requires-Dist: optax
Requires-Dist: optimistix
Requires-Dist: blackjax
Requires-Dist: flowmc>=0.3.0
Requires-Dist: numpyro
Requires-Dist: jaxopt
Requires-Dist: pymc
Requires-Dist: nutpie
Requires-Dist: pytest ; extra == "dev"
Requires-Dist: pytest-xdist ; extra == "dev"
Requires-Dist: pylint>=2.6.0 ; extra == "dev"
Requires-Dist: pyink ; extra == "dev"
Requires-Dist: mkdocs==1.5.3 ; extra == "docs"
Requires-Dist: mkdocs-material==9.5.11 ; extra == "docs"
Requires-Dist: pymdown-extensions==10.7 ; extra == "docs"
Requires-Dist: mkdocstrings==0.24.1 ; extra == "docs"
Requires-Dist: mknotebooks==0.8.0 ; extra == "docs"
Project-URL: changelog, https://github.com/jax-ml/bayeux/blob/main/CHANGELOG.md
Project-URL: documentation, https://jax-ml.github.io/bayeux
Project-URL: homepage, https://github.com/jax-ml/bayeux
Project-URL: repository, https://github.com/jax-ml/bayeux
Provides-Extra: dev
Provides-Extra: docs
